magnet/__init__.py
magnet/datastructs.py
magnet/engine.py
magnet/parser.py
magnet/replacer.py
magnet/snowflake.py
magnet4c-0.0.2.dist-info/LICENSE
magnet4c-0.0.2.dist-info/METADATA
magnet4c-0.0.2.dist-info/WHEEL
magnet4c-0.0.2.dist-info/top_level.txt
magnet4c-0.0.2.dist-info/RECORD
