Metadata-Version: 2.1
Name: magnet4c
Version: 0.0.2
Summary: Corpora operator for multiple file formats.
Home-page: http://at.senhacore.xyz:3000/huang825172/Magnet
Author: huang825172
Author-email: 1048035187@qq.com
License: UNKNOWN
Keywords: corpora parallel file extract replace
Platform: UNKNOWN
Classifier: Development Status :: 1 - Planning
Classifier: Programming Language :: Python :: 3.6
Classifier: License :: OSI Approved :: MIT License
Requires-Python: >=3.6
Requires-Dist: pypandoc
